{
  "$schema": "https://biomejs.dev/schemas/1.9.4/schema.json",
  "organizeImports": {
    "enabled": true
  },
  "linter": {
    "enabled": true,
    "rules": {
      "recommended": true,
      "correctness": {
        "noUnusedVariables": "error",
        "noUndeclaredVariables": "error"
      },
      "style": {
        "useBlockStatements": "error",
        "noNegationElse": "error"
      },
      "suspicious": {
        "noExplicitAny": "warn",
        "noConsoleLog": "warn"
      },
      "security": {
        "noDangerouslySetInnerHtml": "error"
      }
    }
  },
  "formatter": {
    "enabled": true,
    "formatWithErrors": false,
    "indentStyle": "space",
    "indentWidth": 2,
    "lineWidth": 100
  },
  "javascript": {
    "formatter": {
      "quoteStyle": "single",
      "trailingCommas": "es5",
      "semicolons": "always"
    }
  }
}
